shoalsoft/pants_mcp_plugin/__init__.py
shoalsoft/pants_mcp_plugin/goals.py
shoalsoft/pants_mcp_plugin/mcp_server.py
shoalsoft/pants_mcp_plugin/register.py
shoalsoft_pants_mcp_plugin-0.1.0.dist-info/METADATA
shoalsoft_pants_mcp_plugin-0.1.0.dist-info/WHEEL
shoalsoft_pants_mcp_plugin-0.1.0.dist-info/namespace_packages.txt
shoalsoft_pants_mcp_plugin-0.1.0.dist-info/top_level.txt
shoalsoft_pants_mcp_plugin-0.1.0.dist-info/RECORD
