Metadata-Version: 2.4
Name: shoalsoft-pants-mcp-plugin
Version: 0.1.0
Summary: Pantsbuild Model Context Protocol Plugin from Shoal Software LLC
Home-page: https://github.com/shoalsoft/shoalsoft-pants-mcp-plugin
Author: Tom Dyas
Author-email: tom@shoalsoftware.com
Requires-Python: ==3.11.*
Requires-Dist: mcp[cli]==1.14.0
Requires-Dist: pydantic
Dynamic: author
Dynamic: author-email
Dynamic: description
Dynamic: description-content-type
Dynamic: home-page
Dynamic: requires-dist
Dynamic: requires-python
Dynamic: summary
